agent/__init__.py
agent/agent.py
agent/chat.py
agent/default_agent.py
agent/prompt_agent.py
client/__init__.py
client/aws_bedrock.py
client/config.py
client/groq_client.py
memory/__init__.py
memory/chat_buffer_memory.py
memory/chat_memory.py
memory/chat_vector_memory.py
tool/__init__.py
tool/code_executor.py
tool/metadata.py
tool/online_tool.py
type/__init__.py
type/action_permission.py
type/chat_client.py
type/chat_message.py
type/status_code.py
zen_agent-0.1.10.dist-info/METADATA
zen_agent-0.1.10.dist-info/WHEEL
zen_agent-0.1.10.dist-info/top_level.txt
zen_agent-0.1.10.dist-info/RECORD
