Metadata-Version: 2.1
Name: zen-agent
Version: 0.1.10
Summary: ZenAgent facilitates the creation of AI assistant and the development of advanced multi-agent system.
Home-page: https://github.com/yanmxa/zen-agent
Author: Meng Yan
Author-email: yanmxa@gmail.com
Requires-Dist: boto3
